{"subject_id":6,"conceptroom":{"1":{"ordr_of_conceptroom":1,"concept":{"1":{"concept_name":"Nouns, Subject and Predicate","concept_id":1,"activity":{"210":{"activity_name":"3. D.3Identify common and proper nouns","is_anchor":false,"remedial":{"1":{"typecode":"POPUP","remedial_id":269},"2":{"typecode":"VIDEO","remedial_id":270}},"ordr_of_activity":9,"activity_id":210,"skill_id":51,"game_id":1},"211":{"activity_name":"4. D.4Select the nouns","is_anchor":false,"remedial":{"1":{"typecode":"POPUP","remedial_id":266},"2":{"typecode":"VIDEO","remedial_id":271}},"ordr_of_activity":10,"activity_id":211,"skill_id":51,"game_id":58},"212":{"activity_name":"5. D.5Sort common and proper nouns","is_anchor":false,"remedial":{"1":{"typecode":"POPUP","remedial_id":269},"2":{"typecode":"VIDEO","remedial_id":270}},"ordr_of_activity":11,"activity_id":212,"skill_id":51,"game_id":51},"202":{"activity_name":"Identify noun from the sentence","is_anchor":false,"remedial":{"1":{"typecode":"POPUP","remedial_id":268},"2":{"typecode":"VIDEO","remedial_id":267}},"ordr_of_activity":1,"activity_id":202,"skill_id":52,"game_id":1},"213":{"activity_name":"Nouns, subject and predicate","is_anchor":true,"remedial":{"1":{"remedial_id":0},"2":{"remedial_id":0}},"ordr_of_activity":12,"activity_id":213,"skill_id":51,"game_id":1},"203":{"activity_name":"Subject and predicate","is_anchor":false,"remedial":{"1":{"typecode":"POPUP","remedial_id":259},"2":{"typecode":"VIDEO","remedial_id":260}},"ordr_of_activity":2,"activity_id":203,"skill_id":52,"game_id":1},"204":{"activity_name":"1. B.1Identify the subject in a sentence","is_anchor":false,"remedial":{"1":{"typecode":"POPUP","remedial_id":261},"2":{"typecode":"VIDEO","remedial_id":260}},"ordr_of_activity":3,"activity_id":204,"skill_id":52,"game_id":1},"205":{"activity_name":"2. B.2Identify the predicate in a sentence","is_anchor":false,"remedial":{"1":{"typecode":"POPUP","remedial_id":261},"2":{"typecode":"VIDEO","remedial_id":260}},"ordr_of_activity":4,"activity_id":205,"skill_id":52,"game_id":1},"206":{"activity_name":"Identify the proper noun in the sentence","is_anchor":false,"remedial":{"1":{"typecode":"POPUP","remedial_id":269},"2":{"typecode":"VIDEO","remedial_id":270}},"ordr_of_activity":5,"activity_id":206,"skill_id":52,"game_id":1},"207":{"activity_name":"4. C.4Unscramble the words to make a noun","is_anchor":false,"remedial":{"1":{"typecode":"POPUP","remedial_id":268},"2":{"typecode":"VIDEO","remedial_id":267}},"ordr_of_activity":6,"activity_id":207,"skill_id":52,"game_id":18},"208":{"activity_name":"1. D.1Which word is a noun?","is_anchor":false,"remedial":{"1":{"typecode":"POPUP","remedial_id":266},"2":{"typecode":"VIDEO","remedial_id":267}},"ordr_of_activity":7,"activity_id":208,"skill_id":51,"game_id":1},"209":{"activity_name":"2. D.2Identify nouns","is_anchor":false,"remedial":{"1":{"typecode":"POPUP","remedial_id":268},"2":{"typecode":"VIDEO","remedial_id":267}},"ordr_of_activity":8,"activity_id":209,"skill_id":51,"game_id":58}}},"2":{"concept_name":"Singular, plural and subject and verb agreement","concept_id":2,"activity":{"220":{"activity_name":"1. I.1One or more than one?","is_anchor":false,"remedial":{"1":{"typecode":"POPUP","remedial_id":279},"2":{"typecode":"VIDEO","remedial_id":280}},"ordr_of_activity":7,"activity_id":220,"skill_id":51,"game_id":5},"221":{"activity_name":"2. I.2Use the correct subject or verb","is_anchor":false,"remedial":{"1":{"typecode":"POPUP","remedial_id":276},"2":{"typecode":"VIDEO","remedial_id":281}},"ordr_of_activity":8,"activity_id":221,"skill_id":52,"game_id":1},"222":{"activity_name":"3. I.3Pronoun-verb agreement","is_anchor":false,"remedial":{"1":{"typecode":"POPUP","remedial_id":276},"2":{"typecode":"VIDEO","remedial_id":281}},"ordr_of_activity":9,"activity_id":222,"skill_id":51,"game_id":1},"223":{"activity_name":"Singular, plural and subject and verb agreement","is_anchor":true,"remedial":{"1":{"remedial_id":0},"2":{"remedial_id":0}},"ordr_of_activity":10,"activity_id":223,"skill_id":51,"game_id":1},"214":{"activity_name":"1. E.2Use regular plurals with -s and -es","is_anchor":false,"remedial":{"1":{"typecode":"POPUP","remedial_id":272},"2":{"typecode":"VIDEO","remedial_id":273}},"ordr_of_activity":1,"activity_id":214,"skill_id":51,"game_id":1},"215":{"activity_name":"2. E.3Use singular and plural nouns","is_anchor":false,"remedial":{"1":{"typecode":"POPUP","remedial_id":272},"2":{"typecode":"VIDEO","remedial_id":273}},"ordr_of_activity":2,"activity_id":215,"skill_id":51,"game_id":1},"216":{"activity_name":"1. F.1Is the noun singular or plural?","is_anchor":false,"remedial":{"1":{"typecode":"POPUP","remedial_id":272},"2":{"typecode":"VIDEO","remedial_id":274}},"ordr_of_activity":3,"activity_id":216,"skill_id":51,"game_id":5},"217":{"activity_name":"2. F.2Form and use irregular plurals","is_anchor":false,"remedial":{"1":{"typecode":"POPUP","remedial_id":275},"2":{"typecode":"VIDEO","remedial_id":274}},"ordr_of_activity":4,"activity_id":217,"skill_id":51,"game_id":1},"218":{"activity_name":"1. H.1Use action verbs","is_anchor":false,"remedial":{"1":{"typecode":"POPUP","remedial_id":276},"2":{"typecode":"VIDEO","remedial_id":277}},"ordr_of_activity":5,"activity_id":218,"skill_id":51,"game_id":1},"219":{"activity_name":"2. H.2Identify action verbs","is_anchor":false,"remedial":{"1":{"typecode":"POPUP","remedial_id":278},"2":{"typecode":"VIDEO","remedial_id":277}},"ordr_of_activity":6,"activity_id":219,"skill_id":51,"game_id":1}}}},"conceptroom_name":"Subject, predicate and Verb agreement","conceptroom_id":1},"2":{"ordr_of_conceptroom":2,"concept":{"1":{"concept_name":"Regular Past Tense","concept_id":1,"activity":{"231":{"activity_name":"4. L.4To have: Use the correct form","is_anchor":false,"remedial":{"1":{"typecode":"POPUP","remedial_id":290},"2":{"typecode":"VIDEO","remedial_id":244}},"ordr_of_activity":8,"activity_id":231,"skill_id":52,"game_id":1},"232":{"activity_name":"Regular Past Tense","is_anchor":true,"remedial":{"1":{"remedial_id":0},"2":{"remedial_id":0}},"ordr_of_activity":9,"activity_id":232,"skill_id":51,"game_id":1},"224":{"activity_name":"1. J.1Identify verbs in the regular past tense","is_anchor":false,"remedial":{"1":{"typecode":"POPUP","remedial_id":282},"2":{"typecode":"VIDEO","remedial_id":283}},"ordr_of_activity":1,"activity_id":224,"skill_id":51,"game_id":1},"225":{"activity_name":"2. J.2Which sentence is in the regular past tense?","is_anchor":false,"remedial":{"1":{"typecode":"POPUP","remedial_id":282},"2":{"typecode":"VIDEO","remedial_id":283}},"ordr_of_activity":2,"activity_id":225,"skill_id":52,"game_id":1},"226":{"activity_name":"3. J.3Form and use the regular past tense","is_anchor":false,"remedial":{"1":{"typecode":"POPUP","remedial_id":282},"2":{"typecode":"VIDEO","remedial_id":283}},"ordr_of_activity":3,"activity_id":226,"skill_id":51,"game_id":51},"227":{"activity_name":"1. K.1Change the sentence to future tense","is_anchor":false,"remedial":{"1":{"typecode":"POPUP","remedial_id":285},"2":{"typecode":"VIDEO","remedial_id":286}},"ordr_of_activity":4,"activity_id":227,"skill_id":52,"game_id":1},"228":{"activity_name":"2. L.2To be: Use the correct past tense form","is_anchor":false,"remedial":{"1":{"typecode":"POPUP","remedial_id":288},"2":{"typecode":"VIDEO","remedial_id":240}},"ordr_of_activity":5,"activity_id":228,"skill_id":52,"game_id":1},"229":{"activity_name":"2. L.2To be: Use the correct past tense form","is_anchor":false,"remedial":{"1":{"typecode":"POPUP","remedial_id":288},"2":{"typecode":"VIDEO","remedial_id":240}},"ordr_of_activity":6,"activity_id":229,"skill_id":52,"game_id":1},"230":{"activity_name":"3. L.3To be: Use the correct form","is_anchor":false,"remedial":{"1":{"typecode":"POPUP","remedial_id":289},"2":{"typecode":"VIDEO","remedial_id":242}},"ordr_of_activity":7,"activity_id":230,"skill_id":52,"game_id":1}}},"2":{"concept_name":"Irregular Past Tense","concept_id":2,"activity":{"233":{"activity_name":"1. M.1Identify the irregular past tense I","is_anchor":false,"remedial":{"1":{"typecode":"POPUP","remedial_id":291},"2":{"typecode":"VIDEO","remedial_id":236}},"ordr_of_activity":1,"activity_id":233,"skill_id":52,"game_id":1},"234":{"activity_name":"2. M.2Identify the irregular past tense II","is_anchor":false,"remedial":{"1":{"typecode":"POPUP","remedial_id":291},"2":{"typecode":"VIDEO","remedial_id":236}},"ordr_of_activity":2,"activity_id":234,"skill_id":52,"game_id":1},"235":{"activity_name":"3. M.3Form and use the irregular past tense: set 1","is_anchor":false,"remedial":{"1":{"typecode":"POPUP","remedial_id":291},"2":{"typecode":"VIDEO","remedial_id":292}},"ordr_of_activity":3,"activity_id":235,"skill_id":51,"game_id":1},"236":{"activity_name":"4. M.4Form and use the irregular past tense: set 2","is_anchor":false,"remedial":{"1":{"typecode":"POPUP","remedial_id":291},"2":{"typecode":"VIDEO","remedial_id":292}},"ordr_of_activity":4,"activity_id":236,"skill_id":51,"game_id":1},"237":{"activity_name":"5. M.5Form and use the irregular past tense: set 3","is_anchor":false,"remedial":{"1":{"typecode":"POPUP","remedial_id":291},"2":{"typecode":"VIDEO","remedial_id":293}},"ordr_of_activity":5,"activity_id":237,"skill_id":51,"game_id":1},"238":{"activity_name":"6. M.6Form and use the irregular past tense: set 4","is_anchor":false,"remedial":{"1":{"typecode":"POPUP","remedial_id":291},"2":{"typecode":"VIDEO","remedial_id":293}},"ordr_of_activity":6,"activity_id":238,"skill_id":51,"game_id":1},"239":{"activity_name":"7. M.7Place sentences with irregular verbs on a timeline","is_anchor":false,"remedial":{"1":{"typecode":"POPUP","remedial_id":294},"2":{"typecode":"VIDEO","remedial_id":295}},"ordr_of_activity":7,"activity_id":239,"skill_id":52,"game_id":52},"240":{"activity_name":"Irregular past tense","is_anchor":true,"remedial":{"1":{"remedial_id":0},"2":{"remedial_id":0}},"ordr_of_activity":8,"activity_id":240,"skill_id":51,"game_id":1}}}},"conceptroom_name":"Regular-irregular Past Tense","conceptroom_id":2},"3":{"ordr_of_conceptroom":3,"concept":{"1":{"concept_name":"Pronouns","concept_id":1,"activity":{"242":{"activity_name":"2. P.2Choose between subject and object pronouns","is_anchor":false,"remedial":{"1":{"typecode":"POPUP","remedial_id":296},"2":{"typecode":"VIDEO","remedial_id":297}},"ordr_of_activity":2,"activity_id":242,"skill_id":51,"game_id":1},"243":{"activity_name":"3. P.3Replace the singular noun with a pronoun","is_anchor":false,"remedial":{"1":{"typecode":"POPUP","remedial_id":296},"2":{"typecode":"VIDEO","remedial_id":298}},"ordr_of_activity":3,"activity_id":243,"skill_id":51,"game_id":1},"244":{"activity_name":"4. P.4Replace the plural noun with a pronoun","is_anchor":false,"remedial":{"1":{"typecode":"POPUP","remedial_id":296},"2":{"typecode":"VIDEO","remedial_id":298}},"ordr_of_activity":4,"activity_id":244,"skill_id":51,"game_id":1},"245":{"activity_name":"5. P.5Compound subjects and objects with I and me","is_anchor":false,"remedial":{"1":{"typecode":"POPUP","remedial_id":296},"2":{"typecode":"VIDEO","remedial_id":299}},"ordr_of_activity":5,"activity_id":245,"skill_id":51,"game_id":1},"246":{"activity_name":"6. P.6Choose the correct personal pronoun","is_anchor":false,"remedial":{"1":{"typecode":"POPUP","remedial_id":296},"2":{"typecode":"VIDEO","remedial_id":298}},"ordr_of_activity":6,"activity_id":246,"skill_id":51,"game_id":1},"247":{"activity_name":"Pronouns","is_anchor":true,"remedial":{"1":{"remedial_id":0},"2":{"remedial_id":0}},"ordr_of_activity":7,"activity_id":247,"skill_id":51,"game_id":1},"241":{"activity_name":"1. P.1Identify pronouns","is_anchor":false,"remedial":{"1":{"typecode":"POPUP","remedial_id":296},"2":{"typecode":"VIDEO","remedial_id":297}},"ordr_of_activity":1,"activity_id":241,"skill_id":51,"game_id":1}}},"2":{"concept_name":"Types of pronouns","concept_id":2,"activity":{"253":{"activity_name":"Identify the reflexive pronoun","is_anchor":false,"remedial":{"1":{"typecode":"POPUP","remedial_id":304},"2":{"typecode":"VIDEO","remedial_id":303}},"ordr_of_activity":6,"activity_id":253,"skill_id":51,"game_id":1},"254":{"activity_name":"Types of pronouns","is_anchor":true,"remedial":{"1":{"remedial_id":0},"2":{"remedial_id":0}},"ordr_of_activity":7,"activity_id":254,"skill_id":51,"game_id":1},"248":{"activity_name":"1. Q.1Identify possessive pronouns","is_anchor":false,"remedial":{"1":{"typecode":"POPUP","remedial_id":300},"2":{"typecode":"VIDEO","remedial_id":301}},"ordr_of_activity":1,"activity_id":248,"skill_id":51,"game_id":1},"249":{"activity_name":"2. Q.2Use possessive pronouns","is_anchor":false,"remedial":{"1":{"typecode":"POPUP","remedial_id":300},"2":{"typecode":"VIDEO","remedial_id":301}},"ordr_of_activity":2,"activity_id":249,"skill_id":51,"game_id":1},"250":{"activity_name":"1. R.1Choose the correct Reflexive pronoun","is_anchor":false,"remedial":{"1":{"typecode":"POPUP","remedial_id":304},"2":{"typecode":"VIDEO","remedial_id":303}},"ordr_of_activity":3,"activity_id":250,"skill_id":51,"game_id":1},"251":{"activity_name":"2. R.2Use reflexive pronouns","is_anchor":false,"remedial":{"1":{"typecode":"POPUP","remedial_id":304},"2":{"typecode":"VIDEO","remedial_id":303}},"ordr_of_activity":4,"activity_id":251,"skill_id":51,"game_id":1},"252":{"activity_name":"Identify the possessive pronoun","is_anchor":false,"remedial":{"1":{"typecode":"POPUP","remedial_id":300},"2":{"typecode":"VIDEO","remedial_id":301}},"ordr_of_activity":5,"activity_id":252,"skill_id":51,"game_id":1}}},"3":{"concept_name":"Adjectives and degrees","concept_id":3,"activity":{"255":{"activity_name":"1. T.1Use sense words","is_anchor":false,"remedial":{"1":{"typecode":"POPUP","remedial_id":309},"2":{"typecode":"VIDEO","remedial_id":310}},"ordr_of_activity":1,"activity_id":255,"skill_id":51,"game_id":17},"256":{"activity_name":"2. T.2Does the adjective tell you what kind or how many?","is_anchor":false,"remedial":{"1":{"typecode":"POPUP","remedial_id":311},"2":{"typecode":"VIDEO","remedial_id":312}},"ordr_of_activity":2,"activity_id":256,"skill_id":51,"game_id":1},"257":{"activity_name":"3. T.3Identify the adjective that describes the noun","is_anchor":false,"remedial":{"1":{"typecode":"POPUP","remedial_id":313},"2":{"typecode":"VIDEO","remedial_id":312}},"ordr_of_activity":3,"activity_id":257,"skill_id":52,"game_id":1},"258":{"activity_name":"4. T.4Identify adjectives","is_anchor":false,"remedial":{"1":{"typecode":"POPUP","remedial_id":313},"2":{"typecode":"VIDEO","remedial_id":310}},"ordr_of_activity":4,"activity_id":258,"skill_id":52,"game_id":1},"259":{"activity_name":"Adjectives that compare","is_anchor":false,"remedial":{"1":{"typecode":"POPUP","remedial_id":314},"2":{"typecode":"VIDEO","remedial_id":315}},"ordr_of_activity":5,"activity_id":259,"skill_id":52,"game_id":1},"260":{"activity_name":"1. U.1Identify comparative and superlative adjectives","is_anchor":false,"remedial":{"1":{"typecode":"POPUP","remedial_id":316},"2":{"typecode":"VIDEO","remedial_id":315}},"ordr_of_activity":6,"activity_id":260,"skill_id":52,"game_id":1},"261":{"activity_name":"Adjectives and degrees","is_anchor":true,"remedial":{"1":{"remedial_id":0},"2":{"remedial_id":0}},"ordr_of_activity":7,"activity_id":261,"skill_id":52,"game_id":1}}},"4":{"concept_name":"Adverbs","concept_id":4,"activity":{"264":{"activity_name":"Adjectives and adverbs","is_anchor":false,"remedial":{"1":{"typecode":"POPUP","remedial_id":321},"2":{"typecode":"VIDEO","remedial_id":322}},"ordr_of_activity":3,"activity_id":264,"skill_id":52,"game_id":1},"265":{"activity_name":"1. W.1Choose between adjectives and adverbs","is_anchor":false,"remedial":{"1":{"typecode":"POPUP","remedial_id":321},"2":{"typecode":"VIDEO","remedial_id":322}},"ordr_of_activity":4,"activity_id":265,"skill_id":52,"game_id":5},"266":{"activity_name":"2. W.2Is the word an adjective or adverb?","is_anchor":false,"remedial":{"1":{"typecode":"POPUP","remedial_id":321},"2":{"typecode":"VIDEO","remedial_id":322}},"ordr_of_activity":5,"activity_id":266,"skill_id":51,"game_id":5},"267":{"activity_name":"Adverbs","is_anchor":true,"remedial":{"1":{"remedial_id":0},"2":{"remedial_id":0}},"ordr_of_activity":6,"activity_id":267,"skill_id":51,"game_id":5},"262":{"activity_name":"1. V.1Does the adverb tell you how, when or where?","is_anchor":false,"remedial":{"1":{"typecode":"POPUP","remedial_id":317},"2":{"typecode":"VIDEO","remedial_id":318}},"ordr_of_activity":1,"activity_id":262,"skill_id":51,"game_id":1},"263":{"activity_name":"2. V.2Identify adverbs","is_anchor":false,"remedial":{"1":{"typecode":"POPUP","remedial_id":319},"2":{"typecode":"VIDEO","remedial_id":320}},"ordr_of_activity":2,"activity_id":263,"skill_id":51,"game_id":1}}},"5":{"concept_name":"Prepositions","concept_id":5,"activity":{"275":{"activity_name":"Prepositions","is_anchor":true,"remedial":{"1":{"remedial_id":0},"2":{"remedial_id":0}},"ordr_of_activity":8,"activity_id":275,"skill_id":52,"game_id":2},"268":{"activity_name":"1. X.1Select the best preposition to match the picture","is_anchor":false,"remedial":{"1":{"typecode":"POPUP","remedial_id":323},"2":{"typecode":"VIDEO","remedial_id":324}},"ordr_of_activity":1,"activity_id":268,"skill_id":53,"game_id":22},"269":{"activity_name":"2. X.2Select the best preposition to complete the sentence","is_anchor":false,"remedial":{"1":{"typecode":"POPUP","remedial_id":325},"2":{"typecode":"VIDEO","remedial_id":324}},"ordr_of_activity":2,"activity_id":269,"skill_id":52,"game_id":17},"270":{"activity_name":"Preposition","is_anchor":false,"remedial":{"1":{"typecode":"POPUP","remedial_id":416},"2":{"typecode":"VIDEO","remedial_id":324}},"ordr_of_activity":3,"activity_id":270,"skill_id":51,"game_id":22},"271":{"activity_name":"Preposition","is_anchor":false,"remedial":{"1":{"typecode":"POPUP","remedial_id":415},"2":{"typecode":"VIDEO","remedial_id":106}},"ordr_of_activity":4,"activity_id":271,"skill_id":51,"game_id":28},"272":{"activity_name":"Preposition","is_anchor":false,"remedial":{"1":{"typecode":"POPUP","remedial_id":415},"2":{"typecode":"VIDEO","remedial_id":99}},"ordr_of_activity":5,"activity_id":272,"skill_id":52,"game_id":28},"273":{"activity_name":"Preposition","is_anchor":false,"remedial":{"1":{"typecode":"POPUP","remedial_id":414},"2":{"typecode":"VIDEO","remedial_id":99}},"ordr_of_activity":6,"activity_id":273,"skill_id":51,"game_id":22},"274":{"activity_name":"Preposition","is_anchor":false,"remedial":{"1":{"typecode":"POPUP","remedial_id":417},"2":{"typecode":"VIDEO","remedial_id":324}},"ordr_of_activity":7,"activity_id":274,"skill_id":51,"game_id":4}}},"6":{"concept_name":"Conjunctions","concept_id":6,"activity":{"276":{"activity_name":"1. Z.1Use conjunctions","is_anchor":false,"remedial":{"1":{"typecode":"POPUP","remedial_id":329},"2":{"typecode":"VIDEO","remedial_id":200}},"ordr_of_activity":1,"activity_id":276,"skill_id":52,"game_id":17},"277":{"activity_name":"1. Z.1Use conjunctions","is_anchor":false,"remedial":{"1":{"typecode":"POPUP","remedial_id":329},"2":{"typecode":"VIDEO","remedial_id":200}},"ordr_of_activity":2,"activity_id":277,"skill_id":52,"game_id":17},"278":{"activity_name":"1. Z.1Use conjunctions","is_anchor":false,"remedial":{"1":{"typecode":"POPUP","remedial_id":329},"2":{"typecode":"VIDEO","remedial_id":200}},"ordr_of_activity":3,"activity_id":278,"skill_id":52,"game_id":17},"279":{"activity_name":"1. AA.1Identify time-order words","is_anchor":false,"remedial":{"1":{"typecode":"POPUP","remedial_id":330},"2":{"typecode":"VIDEO","remedial_id":331}},"ordr_of_activity":4,"activity_id":279,"skill_id":52,"game_id":1},"280":{"activity_name":"2. AA.2Put the sentences in order","is_anchor":false,"remedial":{"1":{"typecode":"POPUP","remedial_id":332},"2":{"typecode":"VIDEO","remedial_id":333}},"ordr_of_activity":5,"activity_id":280,"skill_id":52,"game_id":29},"281":{"activity_name":"Conjunctions","is_anchor":true,"remedial":{"1":{"remedial_id":0},"2":{"remedial_id":0}},"ordr_of_activity":6,"activity_id":281,"skill_id":51,"game_id":1}}}},"conceptroom_name":"Pronoun, Adjectives, Adverbs, Preposition and Conjunction","conceptroom_id":3},"4":{"ordr_of_conceptroom":4,"concept":{"1":{"concept_name":"Names of people, place and months and salutation","concept_id":1,"activity":{"286":{"activity_name":"1. DD.1Capitalising titles","is_anchor":false,"remedial":{"1":{"typecode":"POPUP","remedial_id":338},"2":{"typecode":"VIDEO","remedial_id":340}},"ordr_of_activity":5,"activity_id":286,"skill_id":51,"game_id":58},"287":{"activity_name":"Names of people, place and months and salutation","is_anchor":true,"remedial":{"1":{"remedial_id":0},"2":{"remedial_id":0}},"ordr_of_activity":6,"activity_id":287,"skill_id":51,"game_id":1},"282":{"activity_name":"1. BB.1Capitalising the names of people and pets","is_anchor":false,"remedial":{"1":{"typecode":"POPUP","remedial_id":334},"2":{"typecode":"VIDEO","remedial_id":335}},"ordr_of_activity":1,"activity_id":282,"skill_id":52,"game_id":1},"283":{"activity_name":"2. BB.2Capitalising days, months and holidays","is_anchor":false,"remedial":{"1":{"typecode":"POPUP","remedial_id":334},"2":{"typecode":"VIDEO","remedial_id":336}},"ordr_of_activity":2,"activity_id":283,"skill_id":52,"game_id":1},"284":{"activity_name":"3. BB.3Capitalising the names of places and geographic features","is_anchor":false,"remedial":{"1":{"typecode":"POPUP","remedial_id":334},"2":{"typecode":"VIDEO","remedial_id":337}},"ordr_of_activity":3,"activity_id":284,"skill_id":52,"game_id":1},"285":{"activity_name":"1. CC.1Greetings and closings of letters","is_anchor":false,"remedial":{"1":{"typecode":"POPUP","remedial_id":338},"2":{"typecode":"VIDEO","remedial_id":339}},"ordr_of_activity":4,"activity_id":285,"skill_id":51,"game_id":1}}},"2":{"concept_name":"Vocabulary and synonyms-antonyms","concept_id":2,"activity":{"288":{"activity_name":"1. EE.1Choose the synonym","is_anchor":false,"remedial":{"1":{"typecode":"POPUP","remedial_id":341},"2":{"typecode":"VIDEO","remedial_id":254}},"ordr_of_activity":1,"activity_id":288,"skill_id":51,"game_id":1},"289":{"activity_name":"2. EE.2Which sentence has the same meaning?","is_anchor":false,"remedial":{"1":{"typecode":"POPUP","remedial_id":341},"2":{"typecode":"VIDEO","remedial_id":342}},"ordr_of_activity":2,"activity_id":289,"skill_id":52,"game_id":58},"290":{"activity_name":"3. EE.3Find synonyms in context","is_anchor":false,"remedial":{"1":{"typecode":"POPUP","remedial_id":341},"2":{"typecode":"VIDEO","remedial_id":254}},"ordr_of_activity":3,"activity_id":290,"skill_id":52,"game_id":1},"291":{"activity_name":"1. FF.1Choose the antonym","is_anchor":false,"remedial":{"1":{"typecode":"POPUP","remedial_id":343},"2":{"typecode":"VIDEO","remedial_id":256}},"ordr_of_activity":4,"activity_id":291,"skill_id":51,"game_id":1},"292":{"activity_name":"2. FF.2Which sentence uses an antonym?","is_anchor":false,"remedial":{"1":{"typecode":"POPUP","remedial_id":343},"2":{"typecode":"VIDEO","remedial_id":344}},"ordr_of_activity":5,"activity_id":292,"skill_id":52,"game_id":1},"293":{"activity_name":"3. FF.3Find antonyms in context","is_anchor":false,"remedial":{"1":{"typecode":"POPUP","remedial_id":345},"2":{"typecode":"VIDEO","remedial_id":256}},"ordr_of_activity":6,"activity_id":293,"skill_id":52,"game_id":1},"294":{"activity_name":"Vocabulary and synonyms-antonyms","is_anchor":true,"remedial":{"1":{"remedial_id":0},"2":{"remedial_id":0}},"ordr_of_activity":7,"activity_id":294,"skill_id":52,"game_id":1}}},"3":{"concept_name":"Synonyms and Antonyms","concept_id":3,"activity":{"297":{"activity_name":"Words with related meanings 1","is_anchor":false,"remedial":{"1":{"typecode":"POPUP","remedial_id":349},"2":{"typecode":"VIDEO","remedial_id":350}},"ordr_of_activity":3,"activity_id":297,"skill_id":51,"game_id":58},"298":{"activity_name":"Words with related meanings 2","is_anchor":false,"remedial":{"1":{"typecode":"POPUP","remedial_id":349},"2":{"typecode":"VIDEO","remedial_id":350}},"ordr_of_activity":4,"activity_id":298,"skill_id":51,"game_id":58},"299":{"activity_name":"Choose the correct Synonym","is_anchor":false,"remedial":{"1":{"typecode":"POPUP","remedial_id":349},"2":{"typecode":"VIDEO","remedial_id":350}},"ordr_of_activity":5,"activity_id":299,"skill_id":51,"game_id":1},"300":{"activity_name":"Synonyms and Antonyms","is_anchor":true,"remedial":{"1":{"remedial_id":0},"2":{"remedial_id":0}},"ordr_of_activity":6,"activity_id":300,"skill_id":51,"game_id":1},"295":{"activity_name":"Match the Following 1","is_anchor":false,"remedial":{"1":{"typecode":"POPUP","remedial_id":349},"2":{"typecode":"VIDEO","remedial_id":350}},"ordr_of_activity":1,"activity_id":295,"skill_id":51,"game_id":13},"296":{"activity_name":"Match the Following 2","is_anchor":false,"remedial":{"1":{"typecode":"POPUP","remedial_id":343},"2":{"typecode":"VIDEO","remedial_id":256}},"ordr_of_activity":2,"activity_id":296,"skill_id":51,"game_id":13}}}},"conceptroom_name":"Naming Words and synonyms-antonyms","conceptroom_id":4}},"floor_id":5}